{
  "project_info": {
    "project_number": "937961018091",
    "firebase_url": "https://calculo-de-imc-a015a.firebaseio.com",
    "project_id": "calculo-de-imc-a015a",
    "storage_bucket": "calculo-de-imc-a015a.appspot.com"
  },
  "client": [
    {
      "client_info": {
        "mobilesdk_app_id": "1:937961018091:android:de001d860a5b7b5d2e64ae",
        "android_client_info": {
          "package_name": "com.pinksplash.imc"
        }
      },
      "oauth_client": [
        {
          "client_id": "937961018091-89m1vpmb8go8gqmm97cmqi5t9j9krm6r.apps.googleusercontent.com",
          "client_type": 3
        }
      ],
      "api_key": [
        {
          "current_key": "AIzaSyD3GIw0EPSrbR6zMYUKF137iMveXAMfJyM"
        }
      ],
      "services": {
        "appinvite_service": {
          "other_platform_oauth_client": [
            {
              "client_id": "937961018091-89m1vpmb8go8gqmm97cmqi5t9j9krm6r.apps.googleusercontent.com",
              "client_type": 3
            }
          ]
        }
      }
    }
  ],
  "configuration_version": "1"
}